reasonify/__init__.py
reasonify/core/api.py
reasonify/core/loop.py
reasonify/examples/__init__.py
reasonify/examples/async.yaml
reasonify/examples/date.yaml
reasonify/examples/dir.yaml
reasonify/examples/file.yaml
reasonify/examples/search.yaml
reasonify/examples/simple_ask.yaml
reasonify/models/shot.py
reasonify/templates/__init__.py
reasonify/templates/chat.j2
reasonify/templates/main.j2
reasonify/tools/__init__.py
reasonify/tools/fetch.py
reasonify/tools/input.py
reasonify/tools/install.py
reasonify/utils/component.py
reasonify/utils/context.py
reasonify/utils/event.py
reasonify/utils/html.py
reasonify/utils/inject.py
reasonify/utils/queue.py
reasonify/utils/run.py
reasonify/utils/serialize.py
reasonify/utils/tool.py
reasonify_headless-0.2.5.3.dist-info/METADATA
reasonify_headless-0.2.5.3.dist-info/WHEEL
reasonify_headless-0.2.5.3.dist-info/entry_points.txt
reasonify_headless-0.2.5.3.dist-info/RECORD
