Metadata-Version: 2.1
Name: reasonify-headless
Version: 0.2.5.3
Summary: headless implementation for the Reasonify Agent
Author-Email: Muspi Merol <me@promplate.dev>
License: MIT
Requires-Python: >=3.12
Requires-Dist: useful-coderunner~=1.0; sys_platform != "emscripten"
Requires-Dist: promplate<0.3.6.0,>=0.3.4.7
Requires-Dist: promptools[validation]~=0.1.3.4
Requires-Dist: promplate-recipes<0.2.4.0,>=0.2.2.1
Requires-Dist: pyyaml~=6.0.1
Requires-Dist: html-text~=0.6.2
Requires-Dist: html2text2~=1.0.0
Requires-Dist: isomorphic-fetch~=0.0.0.0.dev2
